creditpy/__init__.py
creditpy/adjusted_binomial_test.py
creditpy/adjusted_herfindahl_hirschman_index.py
creditpy/anchor_point.py
creditpy/bayesian_calibration.py
creditpy/binomial_test.py
creditpy/calculate_gini.py
creditpy/chisquare_test.py
creditpy/correlation_cluster.py
creditpy/data/german_credit.csv
creditpy/gini_elimination.py
creditpy/gini_univariate.py
creditpy/gini_univariate_data.py
creditpy/herfindahl_hirschman_index.py
creditpy/iv_calc.py
creditpy/iv_calc_data.py
creditpy/iv_elimination.py
creditpy/kfold_cross_validation_glm.py
creditpy/kolmogorov_smirnov.py
creditpy/load_german_credit_data.py
creditpy/master_scale.py
creditpy/max_gini_model.py
creditpy/missing_elimination.py
creditpy/missing_ratio.py
creditpy/na_checker.py
creditpy/na_filler_contvar.py
creditpy/psi_calc_data.py
creditpy/regression_calibration.py
creditpy/scaled_score.py
creditpy/ssi_calc_data.py
creditpy/summary_default_flag.py
creditpy/time_series_gini.py
creditpy/train_test_balanced_split.py
creditpy/train_test_split.py
creditpy/variable_clustering.py
creditpy/variable_clustering_gini.py
creditpy/vif_calc.py
creditpy/woe.py
creditpy/woe_glm_feature_importance.py
creditpy-2.7.dist-info/LICENSE.txt
creditpy-2.7.dist-info/METADATA
creditpy-2.7.dist-info/WHEEL
creditpy-2.7.dist-info/RECORD
